ggwave.cpython-312-i386-linux-gnu.so
ggwave_wheels-0.4.2.5.dist-info/top_level.txt
ggwave_wheels-0.4.2.5.dist-info/RECORD
ggwave_wheels-0.4.2.5.dist-info/METADATA
ggwave_wheels-0.4.2.5.dist-info/WHEEL
