Metadata-Version: 2.1
Name: ggwave-wheels
Version: 0.4.2.5
Summary: Tiny data-over-sound library.
Home-page: https://github.com/ggerganov/ggwave
Author: Georgi Gerganov
Author-email: Georgi Gerganov <ggerganov@gmail.com>
License: MIT
Project-URL: Homepage, https://github.com/ggerganov/ggwave
Keywords: data-over-sound,fsk,ecc,serverless,pairing,qrcode,ultrasound
Requires-Python: >=3.8
